{
    "description": "",
    "tags": [],
    "size": {
        "height": 1000,
        "width": 2048
    },
    "objects": [
        {
            "id": 6350614,
            "classId": 8738,
            "description": "",
            "geometryType": "rectangle",
            "labelerLogin": "gr@datasetninja.com",
            "createdAt": "2023-06-14T09:40:11.295Z",
            "updatedAt": "2023-06-14T09:40:11.295Z",
            "tags": [],
            "classTitle": "oil_spot",
            "points": {
                "exterior": [
                    [
                        25,
                        351
                    ],
                    [
                        128,
                        451
                    ]
                ],
                "interior": []
            }
        },
        {
            "id": 6350613,
            "classId": 8738,
            "description": "",
            "geometryType": "rectangle",
            "labelerLogin": "gr@datasetninja.com",
            "createdAt": "2023-06-14T09:40:11.294Z",
            "updatedAt": "2023-06-14T09:40:11.294Z",
            "tags": [],
            "classTitle": "oil_spot",
            "points": {
                "exterior": [
                    [
                        18,
                        537
                    ],
                    [
                        140,
                        615
                    ]
                ],
                "interior": []
            }
        }
    ]
}