{
    "description": "",
    "tags": [],
    "size": {
        "height": 1000,
        "width": 2048
    },
    "objects": [
        {
            "id": 6350491,
            "classId": 8738,
            "description": "",
            "geometryType": "rectangle",
            "labelerLogin": "gr@datasetninja.com",
            "createdAt": "2023-06-14T09:40:07.014Z",
            "updatedAt": "2023-06-14T09:40:07.014Z",
            "tags": [],
            "classTitle": "oil_spot",
            "points": {
                "exterior": [
                    [
                        171,
                        180
                    ],
                    [
                        289,
                        266
                    ]
                ],
                "interior": []
            }
        },
        {
            "id": 6350490,
            "classId": 8738,
            "description": "",
            "geometryType": "rectangle",
            "labelerLogin": "gr@datasetninja.com",
            "createdAt": "2023-06-14T09:40:07.013Z",
            "updatedAt": "2023-06-14T09:40:07.013Z",
            "tags": [],
            "classTitle": "oil_spot",
            "points": {
                "exterior": [
                    [
                        167,
                        940
                    ],
                    [
                        295,
                        999
                    ]
                ],
                "interior": []
            }
        }
    ]
}