{
    "description": "",
    "tags": [],
    "size": {
        "height": 1000,
        "width": 2048
    },
    "objects": [
        {
            "id": 6353201,
            "classId": 8737,
            "description": "",
            "geometryType": "rectangle",
            "labelerLogin": "gr@datasetninja.com",
            "createdAt": "2023-06-14T09:44:54.019Z",
            "updatedAt": "2023-06-14T09:44:54.019Z",
            "tags": [],
            "classTitle": "water_spot",
            "points": {
                "exterior": [
                    [
                        1938,
                        355
                    ],
                    [
                        2047,
                        552
                    ]
                ],
                "interior": []
            }
        }
    ]
}