{
    "description": "",
    "tags": [],
    "size": {
        "height": 1000,
        "width": 2048
    },
    "objects": [
        {
            "id": 6352670,
            "classId": 8743,
            "description": "",
            "geometryType": "rectangle",
            "labelerLogin": "gr@datasetninja.com",
            "createdAt": "2023-06-14T09:43:48.738Z",
            "updatedAt": "2023-06-14T09:43:48.738Z",
            "tags": [],
            "classTitle": "waist folding",
            "points": {
                "exterior": [
                    [
                        199,
                        71
                    ],
                    [
                        1671,
                        896
                    ]
                ],
                "interior": []
            }
        }
    ]
}