{
    "description": "",
    "tags": [],
    "size": {
        "height": 1000,
        "width": 2048
    },
    "objects": [
        {
            "id": 6353075,
            "classId": 8736,
            "description": "",
            "geometryType": "rectangle",
            "labelerLogin": "gr@datasetninja.com",
            "createdAt": "2023-06-14T09:44:39.512Z",
            "updatedAt": "2023-06-14T09:44:39.512Z",
            "tags": [],
            "classTitle": "crescent_gap",
            "points": {
                "exterior": [
                    [
                        138,
                        1
                    ],
                    [
                        387,
                        293
                    ]
                ],
                "interior": []
            }
        },
        {
            "id": 6353074,
            "classId": 8735,
            "description": "",
            "geometryType": "rectangle",
            "labelerLogin": "gr@datasetninja.com",
            "createdAt": "2023-06-14T09:44:39.511Z",
            "updatedAt": "2023-06-14T09:44:39.511Z",
            "tags": [],
            "classTitle": "welding_line",
            "points": {
                "exterior": [
                    [
                        5,
                        16
                    ],
                    [
                        212,
                        60
                    ]
                ],
                "interior": []
            }
        }
    ]
}