{
    "description": "",
    "tags": [],
    "size": {
        "height": 1000,
        "width": 2048
    },
    "objects": [
        {
            "id": 6353428,
            "classId": 8737,
            "description": "",
            "geometryType": "rectangle",
            "labelerLogin": "gr@datasetninja.com",
            "createdAt": "2023-06-14T09:45:25.085Z",
            "updatedAt": "2023-06-14T09:45:25.085Z",
            "tags": [],
            "classTitle": "water_spot",
            "points": {
                "exterior": [
                    [
                        592,
                        40
                    ],
                    [
                        813,
                        171
                    ]
                ],
                "interior": []
            }
        }
    ]
}